{"name":"React-google-map","tagline":"React component to render a map with markers from Google Maps API","body":"# react-google-map ![npm](https://img.shields.io/npm/v/react-google-map.svg) ![license](https://img.shields.io/npm/l/react-google-map.svg)\r\n\r\nReact component to render a map with markers from Google Maps API\r\n\r\n![react-google-map example](/screenshots/react-google-map-exemple.png)\r\n\r\n## Install\r\n\r\n```sh\r\nnpm install --save react-google-map\r\n```\r\n\r\n## Changelog\r\n\r\nSee [changelog](./CHANGELOG.md)\r\n\r\n## Demo \r\n\r\n<http://cedricdelpoux.github.io/react-google-map/>\r\n\r\n## Usage\r\n\r\n```js\r\nimport React, { Component } from 'react'\r\nimport GooglePlacesSuggest from 'react-google-map'\r\n\r\nexport default class MyComponent extends Component {\r\n  state = {\r\n    search: '',\r\n    selectedCoordinate: null,\r\n  }\r\n\r\n  handleSearchChange = (e) => {\r\n    this.setState({ search: e.target.value })\r\n  }\r\n\r\n  handleSelectSuggest = (suggestName, coordinate) => {\r\n    this.setState({ search: suggestName, selectedCoordinate: coordinate })\r\n  }\r\n\r\n  render() {\r\n    const { search } = this.state\r\n\r\n    return (\r\n      <GooglePlacesSuggest onSelectSuggest={ this.handleSelectSuggest } search={ search }>\r\n        <input\r\n          type=\"text\"\r\n          value={ search }\r\n          placeholder=\"Search a location\"\r\n          onChange={ this.handleSearchChange }\r\n        />\r\n      </GooglePlacesSuggest>\r\n    )\r\n  }\r\n}\r\n```\r\n\r\n## Props\r\n\r\n  * `coordinates`: Array of objects with shape { description: String, latitude: Number, longitude: Number, title: String } - by default is []\r\n  * `defaultLat`: Number,\r\n  * `defaultLng`: Number,\r\n  * `googleMaps`: Object - injected by decorator,\r\n  * `onChange`: Function with two parameters (New coordinates object, actual zoom),\r\n  * `zoom`: Number - isRequired,\r\n\r\n## Classes\r\n\r\n  * `.googleMap`\r\n\r\n## Development\r\n\r\n### Clean `lib` folder\r\n\r\n```js\r\nnpm run clean\r\n```\r\n\r\n### Build `lib` folder\r\n\r\n```js\r\nnpm run build\r\n```\r\n\r\n### Watch `src` folder\r\n\r\n```js\r\nnpm run watch\r\n```\r\n\r\n### Lint `src` folder\r\n\r\n```js\r\nnpm run lint\r\n```\r\n\r\n## License\r\n\r\nSee [MIT](./LICENCE)\r\n","google":"","note":"Don't delete this file! It's used internally to help with page regeneration."}